{
    "object": "str",
    "{linear, square, exponential}": "str",
    "int, RandomState instance or None": "int",
    "int or float": "float",
    "{squared_error, friedman_mse, absolute_error, poisson}": "str",
    "{best, random}": "str",
    "int, float or {sqrt, log2}": "float",
    "non-negative float": "float",
    "{mean, median, quantile, constant}": "str",
    "int or float or array-like of shape (n_outputs,)": "int",
    "float in [0.0, 1.0]": "float",
    "bool or array-like of shape (n_features, n_features), default=False": "bool",
    "int, RandomState instance": "int",
    "{cyclic, random}": "str",
    "float or list of float": "float",
    "array-like": "list",
    "auto, bool or array-like of shape (n_features, n_features)": "bool",
    "int, cross-validation generator or iterable": "int",
    "bool or int": "bool",
    "{squared_error, friedman_mse, absolute_error, poisson}, default=squared_error": "str",
    "{random, best}": "str",
    "int, float, {sqrt, log2} or None": "float",
    "{squared_error, absolute_error, friedman_mse, poisson}, default=squared_error": "str",
    "{sqrt, log2, None}, int or float": "float",
    "bool or callable": "bool",
    "{lbfgs, newton-cholesky}": "str",
    "kernel instance": "str",
    "float or ndarray of shape (n_samples,)": "float",
    "fmin_l_bfgs_b, callable or None": "str",
    "{squared_error, absolute_error, huber, quantile}, default=squared_error": "str",
    "{friedman_mse, squared_error}": "str",
    "int or None": "int",
    "estimator or zero": "str",
    "{sqrt, log2}, int or float": "float",
    "{squared_error, absolute_error, gamma, poisson, quantile}, default=squared_error": "str",
    "array-like of {bool, int, str} of shape (n_features) or shape (n_categorical_features,)": "bool",
    "array-like of int of shape (n_features) or dict": "list",
    "{pairwise, no_interactions} or sequence of lists/tuples/sets of int": "str",
    "auto or bool": "str",
    "str or callable or None": "str",
    "int or float or None": "float",
    "{nan, clip, raise}": "str",
    "bool or auto": "bool",
    "{uniform, distance}, callable or None": "str",
    "{auto, ball_tree, kd_tree, brute}": "str",
    "str, DistanceMetric object or callable": "str",
    "float or array-like of shape (n_targets,)": "float",
    "str or callable": "str",
    "bool, auto or array-like": "bool",
    "bool, auto or array-like ": "bool",
    "int, cross-validation generator or an iterable": "int",
    "{aic, bic}": "str",
    "{epsilon_insensitive, squared_epsilon_insensitive}, default=epsilon_insensitive": "str",
    "array-like of shape(n_layers - 2,)": "list",
    "{identity, logistic, tanh, relu}": "str",
    "{lbfgs, sgd, adam}": "str",
    "{constant, invscaling, adaptive}": "str",
    "{linear, poly, rbf, sigmoid, precomputed} or callable, default=rbf": "str",
    "{scale, auto} or float": "str",
    "{nipals, svd}": "str",
    "{highs-ds, highs-ipm, highs, interior-point, revised simplex}": "str",
    "int (>= 1) or float ([0, 1])": "float",
    "callable": "str",
    "float in range [0, 1]": "float",
    "str, callable": "str",
    "{float, ndarray of shape (n_targets,)}": "float",
    "{auto, svd, cholesky, lsqr, sparse_cg, sag, saga, lbfgs}": "str",
    "array-like of shape (n_alphas,)": "list",
    "{auto, svd, eigen}": "str",
    "{l2, l1, elasticnet, None}": "str",
    "float or None": "float",
    "function": "str",
    "{auto, identity, log}": "str"
}